zchop/__init__.py
zchop/zchop.py
zchop-0.1.0.dist-info/METADATA
zchop-0.1.0.dist-info/WHEEL
zchop-0.1.0.dist-info/top_level.txt
zchop-0.1.0.dist-info/RECORD
