Metadata-Version: 2.1
Name: zchop
Version: 0.1.0
Summary: Replace small numbers with zero
Author: John Lapeyre
License: MIT
Project-URL: Home, http://github.com/jlapeyre/find_julia
Classifier: Framework :: Django
Classifier: License :: OSI Approved :: MIT License
Classifier: Programming Language :: Python :: 3
Requires-Dist: numpy
